{
    "status": 200,
    "message": "success",
    "data": {
        "id": "V5nqM9Mc8mufp9wmn9CD4g==",
        "title": "Jelly Mangkuk Santan Bubuk",
        "slug": "jelly-mangkuk-santan-bubuk",
        "cover_url": "content-images\/images\/20250521\/KsoGSeD0kCcpxlaBMRPwFgVutq2QZfqz-31373437373939353035d41d8cd98f00b204e9800998ecf8427e.jpg?x-oss-process=image\/format,webp",
        "cover_url_watermark": "content-images\/images\/20250521\/KsoGSeD0kCcpxlaBMRPwFgVutq2QZfqz-31373437373939353035d41d8cd98f00b204e9800998ecf8427e.jpg?x-oss-process=image\/resize,w_600,h_315,m_fill,image\/watermark,image_Y29udGVudC1pbWFnZXMvaW1hZ2VzLzIwMjMwNzMxL3dhdGVybWFyay1hcnRpY2xlLnBuZz94LW9zcy1wcm9jZXNzPWltYWdlL3Jlc2l6ZSxQXzEwMA==,g_south,y_0",
        "description": "Rasanya gurih dan manisnya pas...",
        "rating": 5,
        "video_url": "",
        "price": 10000,
        "price_premium": 0,
        "calories": "",
        "is_cvc": false,
        "cooking_time": 10,
        "serving_min": 2,
        "serving_max": 3,
        "release_date": 1747825440,
        "updated_date": 1747825501,
        "is_bookmark": false,
        "is_editorial": false,
        "rating_user": 0,
        "is_video": false,
        "premium_content": false,
        "brand_slug": "",
        "ingredient_count": 6,
        "meta_title": "",
        "meta_description": "",
        "og_caption": "",
        "og_title": "",
        "og_description": "",
        "og_media": "",
        "rater_count": 1,
        "recook_count": 0,
        "original_image": "content-images\/images\/20250521\/KsoGSeD0kCcpxlaBMRPwFgVutq2QZfqz-31373437373939353035d41d8cd98f00b204e9800998ecf8427e.jpg?x-oss-process=image\/resize,w_800,h_800,m_fixed",
        "share_link": "https:\/\/app.yummy.co.id\/AHUd7CstjmQa9NLf8",
        "category": {
            "name": "",
            "slug": ""
        },
        "cooking_step": [
            {
                "title": "Langkah 1",
                "text": "Campurkan bubuk jelly, dan santan bubuk.",
                "image_url": "content-images\/images\/20250521\/Sdg3TOGKVDH8yDqVJkN0g7vSawogWupf-31373437373939373133d41d8cd98f00b204e9800998ecf8427e.jpg?x-oss-process=image\/resize,w_600,h_600,m_fixed,image\/format,webp",
                "order": 1,
                "start_at": 0,
                "original_image": "content-images\/images\/20250521\/Sdg3TOGKVDH8yDqVJkN0g7vSawogWupf-31373437373939373133d41d8cd98f00b204e9800998ecf8427e.jpg?x-oss-process=image\/format,webp"
            },
            {
                "title": "Langkah 2",
                "text": "Tambahkan sedikit air lalu aduk sampai larut.",
                "image_url": "content-images\/images\/20250521\/8TgRaWIvP5eO8cooXNqBPdfR1fisbS9P-31373437373939373237d41d8cd98f00b204e9800998ecf8427e.jpg?x-oss-process=image\/resize,w_600,h_600,m_fixed,image\/format,webp",
                "order": 2,
                "start_at": 0,
                "original_image": "content-images\/images\/20250521\/8TgRaWIvP5eO8cooXNqBPdfR1fisbS9P-31373437373939373237d41d8cd98f00b204e9800998ecf8427e.jpg?x-oss-process=image\/format,webp"
            },
            {
                "title": "Langkah 3",
                "text": "Masukkan gula dan garam, aduk.",
                "image_url": "content-images\/images\/20250521\/NTr82EIPf3zF5rjq3USTisOgJxLNVBxr-31373437373939373336d41d8cd98f00b204e9800998ecf8427e.jpg?x-oss-process=image\/resize,w_600,h_600,m_fixed,image\/format,webp",
                "order": 3,
                "start_at": 0,
                "original_image": "content-images\/images\/20250521\/NTr82EIPf3zF5rjq3USTisOgJxLNVBxr-31373437373939373336d41d8cd98f00b204e9800998ecf8427e.jpg?x-oss-process=image\/format,webp"
            },
            {
                "title": "Langkah 4",
                "text": "Tambahkan kental manis. Aduk rata, tuangkan sisa air. Masak sambil diaduk hingga mendidih.",
                "image_url": "content-images\/images\/20250521\/vyrP1FmI2HacqH8ICrhpqGN5MYvlyZkf-31373437373939373534d41d8cd98f00b204e9800998ecf8427e.jpg?x-oss-process=image\/resize,w_600,h_600,m_fixed,image\/format,webp",
                "order": 4,
                "start_at": 0,
                "original_image": "content-images\/images\/20250521\/vyrP1FmI2HacqH8ICrhpqGN5MYvlyZkf-31373437373939373534d41d8cd98f00b204e9800998ecf8427e.jpg?x-oss-process=image\/format,webp"
            },
            {
                "title": "Langkah 5",
                "text": "Tunggu hingga uap panas berkurang. Masukkan ke dalam cetakan setengah bola. Buarkan set.",
                "image_url": "content-images\/images\/20250521\/7XcVZVUDan1yepaB1BHauAznEgiDu3Ln-31373437373939373733d41d8cd98f00b204e9800998ecf8427e.jpg?x-oss-process=image\/resize,w_600,h_600,m_fixed,image\/format,webp",
                "order": 5,
                "start_at": 0,
                "original_image": "content-images\/images\/20250521\/7XcVZVUDan1yepaB1BHauAznEgiDu3Ln-31373437373939373733d41d8cd98f00b204e9800998ecf8427e.jpg?x-oss-process=image\/format,webp"
            }
        ],
        "tags": [
            {
                "id": "jAODLSyz_Q2NidSI7J1Gow==",
                "name": "Makanan Penutup",
                "slug": "makanan-penutup"
            },
            {
                "id": "KaA0qS-HqQxSqWP_73RvpQ==",
                "name": "Resep Camilan",
                "slug": "camilan"
            },
            {
                "id": "XPiIeXTytIkJa_n6ueUNAg==",
                "name": "Makanan Indonesia",
                "slug": "makanan-indonesia"
            }
        ],
        "tag_ingredients": [
            {
                "id": "f2-vjYo530gQwFneaPevQg==",
                "name": "Bubuk Jelly",
                "slug": "bubuk-jelly"
            },
            {
                "id": "OVn1FXRZPmVFgDCUzl3xLw==",
                "name": "Santan",
                "slug": "santan"
            },
            {
                "id": "w3SbGgccOQEmv7n7X873eg==",
                "name": "Susu",
                "slug": "susu"
            }
        ],
        "recipe_info": [
            {
                "name": "Halal",
                "slug": "halal",
                "media_url": ""
            }
        ],
        "author": {
            "id": "AwQyebM5piRhty_-sRmF6Q==",
            "uuid": "9dc3c941-f237-4914-8f70-d0795b3cbda1",
            "username": "akuzayyy",
            "name": "Zainab",
            "avatar": "content-images\/avatar\/default.png?x-oss-process=image\/resize,w_200,h_200,m_fixed,image\/format,webp",
            "is_following": false,
            "is_official": false
        },
        "ingredient_type": [
            {
                "name": "Bahan Utama",
                "ingredients": [
                    {
                        "description": "20 gr bubuk jelly coklat",
                        "recommendation": "",
                        "brand": "",
                        "buy_url": "",
                        "media_url": "",
                        "recomendation_media_url": "",
                        "related_recipe": null
                    },
                    {
                        "description": "13 gr santan bubuk",
                        "recommendation": "",
                        "brand": "",
                        "buy_url": "",
                        "media_url": "",
                        "recomendation_media_url": "",
                        "related_recipe": null
                    },
                    {
                        "description": "37 gr susu kental manis",
                        "recommendation": "",
                        "brand": "",
                        "buy_url": "",
                        "media_url": "",
                        "recomendation_media_url": "",
                        "related_recipe": null
                    },
                    {
                        "description": "2 sdm gula",
                        "recommendation": "",
                        "brand": "",
                        "buy_url": "",
                        "media_url": "",
                        "recomendation_media_url": "",
                        "related_recipe": null
                    },
                    {
                        "description": "\u2150 sdt garam",
                        "recommendation": "",
                        "brand": "",
                        "buy_url": "",
                        "media_url": "",
                        "recomendation_media_url": "",
                        "related_recipe": null
                    },
                    {
                        "description": "400 ml air",
                        "recommendation": "",
                        "brand": "",
                        "buy_url": "",
                        "media_url": "",
                        "recomendation_media_url": "",
                        "related_recipe": null
                    }
                ]
            }
        ],
        "nutrition": [],
        "recook": [],
        "cooking_tool": [],
        "tips_and_trick": [],
        "purchase_detail": []
    }
}