{
    "status": 200,
    "message": "success",
    "data": {
        "id": "M7brCmVIrEHpWC0bvRrE9g==",
        "title": "Sayap Ayam Saus Mentega",
        "slug": "sayap-ayam-saus-mentega",
        "cover_url": "content-images\/images\/20250309\/UE4EKQdSqj7Gfpzs2iogdC8Hl4yiLGb3-31373431353131373835d41d8cd98f00b204e9800998ecf8427e.jpg?x-oss-process=image\/format,webp",
        "cover_url_watermark": "content-images\/images\/20250309\/UE4EKQdSqj7Gfpzs2iogdC8Hl4yiLGb3-31373431353131373835d41d8cd98f00b204e9800998ecf8427e.jpg?x-oss-process=image\/resize,w_600,h_315,m_fill,image\/watermark,image_Y29udGVudC1pbWFnZXMvaW1hZ2VzLzIwMjMwNzMxL3dhdGVybWFyay1hcnRpY2xlLnBuZz94LW9zcy1wcm9jZXNzPWltYWdlL3Jlc2l6ZSxQXzEwMA==,g_south,y_0",
        "description": "Sayap ayam saus mentega, cocok banget buat yang suka makanan gurih dan sedikit manis. Ayamnya juicy, saus menteganya kaya rasa, dijamin langsung habis nasi satu piring deh!",
        "rating": 5,
        "video_url": "",
        "price": 35000,
        "price_premium": 0,
        "calories": "",
        "is_cvc": false,
        "cooking_time": 30,
        "serving_min": 2,
        "serving_max": 2,
        "release_date": 1745254020,
        "updated_date": 1745254129,
        "is_bookmark": false,
        "is_editorial": false,
        "rating_user": 0,
        "is_video": false,
        "premium_content": false,
        "brand_slug": "",
        "ingredient_count": 19,
        "meta_title": "",
        "meta_description": "",
        "og_caption": "",
        "og_title": "",
        "og_description": "",
        "og_media": "",
        "rater_count": 1,
        "recook_count": 0,
        "original_image": "content-images\/images\/20250309\/UE4EKQdSqj7Gfpzs2iogdC8Hl4yiLGb3-31373431353131373835d41d8cd98f00b204e9800998ecf8427e.jpg?x-oss-process=image\/resize,w_800,h_800,m_fixed",
        "share_link": "https:\/\/app.yummy.co.id\/dnaEaJcX4UUoATHu8",
        "category": {
            "name": "",
            "slug": ""
        },
        "cooking_step": [
            {
                "title": "Langkah 1",
                "text": "Marinasi sayap ayam dengan garam, kaldu bubuk, bawang putih bubuk dan lada bubuk, selama 30 menit.",
                "image_url": "content-images\/images\/20250309\/eeuAhE1Shv9V0SeqFunJAqp8dGtE9fQE-31373431353131383132d41d8cd98f00b204e9800998ecf8427e.jpg?x-oss-process=image\/resize,w_600,h_600,m_fixed,image\/format,webp",
                "order": 1,
                "start_at": 0,
                "original_image": "content-images\/images\/20250309\/eeuAhE1Shv9V0SeqFunJAqp8dGtE9fQE-31373431353131383132d41d8cd98f00b204e9800998ecf8427e.jpg?x-oss-process=image\/format,webp"
            },
            {
                "title": "Langkah 2",
                "text": "Tambahkan tepung maizena, lalu aduk rata.",
                "image_url": "content-images\/images\/20250309\/3uKJaxTU4RcJXE7BHNwQod8ghGbbR7F8-31373431353131383330d41d8cd98f00b204e9800998ecf8427e.jpg?x-oss-process=image\/resize,w_600,h_600,m_fixed,image\/format,webp",
                "order": 2,
                "start_at": 0,
                "original_image": "content-images\/images\/20250309\/3uKJaxTU4RcJXE7BHNwQod8ghGbbR7F8-31373431353131383330d41d8cd98f00b204e9800998ecf8427e.jpg?x-oss-process=image\/format,webp"
            },
            {
                "title": "Langkah 3",
                "text": "Panaskan minyak goreng, lalu goreng sayap ayam hingga matang. Sisihkan.",
                "image_url": "content-images\/images\/20250309\/Z3HEOr39vLtyS2urN9uDFM3I0PCHcRqi-31373431353131383338d41d8cd98f00b204e9800998ecf8427e.jpg?x-oss-process=image\/resize,w_600,h_600,m_fixed,image\/format,webp",
                "order": 3,
                "start_at": 0,
                "original_image": "content-images\/images\/20250309\/Z3HEOr39vLtyS2urN9uDFM3I0PCHcRqi-31373431353131383338d41d8cd98f00b204e9800998ecf8427e.jpg?x-oss-process=image\/format,webp"
            },
            {
                "title": "Langkah 4",
                "text": "Panaskan mentega, lalu tumis bawang putih dan bawang bombay hingga harum. Tambahkan air, saos tomat, kecap manis, saos tiram, garam, kaldu bubuk, lada bubuk dan gula pasir. Aduk rata.",
                "image_url": "content-images\/images\/20250309\/pU4wPrCQ0LsCR7s07Q86foAmsjxzoh3i-31373431353131383432d41d8cd98f00b204e9800998ecf8427e.jpg?x-oss-process=image\/resize,w_600,h_600,m_fixed,image\/format,webp",
                "order": 4,
                "start_at": 0,
                "original_image": "content-images\/images\/20250309\/pU4wPrCQ0LsCR7s07Q86foAmsjxzoh3i-31373431353131383432d41d8cd98f00b204e9800998ecf8427e.jpg?x-oss-process=image\/format,webp"
            },
            {
                "title": "Langkah 5",
                "text": "Tambahkan sayap ayam dan larutan maizena. Aduk rata lalu angkat dan sajikan.",
                "image_url": "content-images\/images\/20250309\/btTOqAqDO0CgkGTC9sz2QDuXd0RaZHHY-31373431353131383435d41d8cd98f00b204e9800998ecf8427e.jpg?x-oss-process=image\/resize,w_600,h_600,m_fixed,image\/format,webp",
                "order": 5,
                "start_at": 0,
                "original_image": "content-images\/images\/20250309\/btTOqAqDO0CgkGTC9sz2QDuXd0RaZHHY-31373431353131383435d41d8cd98f00b204e9800998ecf8427e.jpg?x-oss-process=image\/format,webp"
            }
        ],
        "tags": [
            {
                "id": "6aBOthKNa-VwyAhY6H31dA==",
                "name": "Makanan Utama",
                "slug": "makanan-utama"
            },
            {
                "id": "XPiIeXTytIkJa_n6ueUNAg==",
                "name": "Makanan Indonesia",
                "slug": "makanan-indonesia"
            },
            {
                "id": "eSjxzes6JPu0bFRNSnMkqg==",
                "name": "Makanan Anak Kost",
                "slug": "makanan-anak-kost"
            }
        ],
        "tag_ingredients": [
            {
                "id": "Lhi3GDcz26NnsIHt9zeeMA==",
                "name": "Ayam",
                "slug": "ayam"
            },
            {
                "id": "Nrc3f1w5lg_NgrGxtxmMhw==",
                "name": "Bawang Putih",
                "slug": "bawang-putih"
            },
            {
                "id": "6aBOthKNa-VwyAhY6H31dA==",
                "name": "Mentega",
                "slug": "mentega"
            },
            {
                "id": "Y7u7FDSxNd95soU0OFqofw==",
                "name": "Tepung Maizena",
                "slug": "tepung-maizena"
            }
        ],
        "recipe_info": [],
        "author": {
            "id": "L2Lr2EShoBzx_79wkov8dQ==",
            "uuid": "85a567d1-9f91-4de3-b5d8-8eb13e4a49a9",
            "username": "dapur-mama1",
            "name": "iis",
            "avatar": "content-images\/images\/20230321\/WK4Hb1s261sUfPJIJDgARk2EAU0mO8wp-31363739333535303737d41d8cd98f00b204e9800998ecf8427e.jpg?x-oss-process=image\/resize,w_200,h_200,m_fixed,image\/format,webp",
            "is_following": false,
            "is_official": false
        },
        "ingredient_type": [
            {
                "name": "Bahan Utama",
                "ingredients": [
                    {
                        "description": "5 buah sayap ayam",
                        "recommendation": "",
                        "brand": "",
                        "buy_url": "",
                        "media_url": "",
                        "recomendation_media_url": "",
                        "related_recipe": null
                    },
                    {
                        "description": "4 sdm tepung maizena",
                        "recommendation": "",
                        "brand": "",
                        "buy_url": "",
                        "media_url": "",
                        "recomendation_media_url": "",
                        "related_recipe": null
                    },
                    {
                        "description": "1\/2 sdt garam",
                        "recommendation": "",
                        "brand": "",
                        "buy_url": "",
                        "media_url": "",
                        "recomendation_media_url": "",
                        "related_recipe": null
                    },
                    {
                        "description": "1\/2 sdt kaldu bubuk",
                        "recommendation": "",
                        "brand": "",
                        "buy_url": "",
                        "media_url": "",
                        "recomendation_media_url": "",
                        "related_recipe": null
                    },
                    {
                        "description": "1\/2 sdt bawang putih bubuk",
                        "recommendation": "",
                        "brand": "",
                        "buy_url": "",
                        "media_url": "",
                        "recomendation_media_url": "",
                        "related_recipe": null
                    },
                    {
                        "description": "1\/2 sdt lada bubuk",
                        "recommendation": "",
                        "brand": "",
                        "buy_url": "",
                        "media_url": "",
                        "recomendation_media_url": "",
                        "related_recipe": null
                    },
                    {
                        "description": "250 ml minyak goreng",
                        "recommendation": "",
                        "brand": "",
                        "buy_url": "",
                        "media_url": "",
                        "recomendation_media_url": "",
                        "related_recipe": null
                    }
                ]
            },
            {
                "name": "Bahan Saus",
                "ingredients": [
                    {
                        "description": "1 buah bawang bombay, iris",
                        "recommendation": "",
                        "brand": "",
                        "buy_url": "",
                        "media_url": "",
                        "recomendation_media_url": "",
                        "related_recipe": null
                    },
                    {
                        "description": "2 siung bawang putih, cincang",
                        "recommendation": "",
                        "brand": "",
                        "buy_url": "",
                        "media_url": "",
                        "recomendation_media_url": "",
                        "related_recipe": null
                    },
                    {
                        "description": "2 sdm mentega",
                        "recommendation": "",
                        "brand": "",
                        "buy_url": "",
                        "media_url": "",
                        "recomendation_media_url": "",
                        "related_recipe": null
                    },
                    {
                        "description": "1 sdm saos tomat",
                        "recommendation": "",
                        "brand": "",
                        "buy_url": "",
                        "media_url": "",
                        "recomendation_media_url": "",
                        "related_recipe": null
                    },
                    {
                        "description": "1 sdm kecap manis",
                        "recommendation": "",
                        "brand": "",
                        "buy_url": "",
                        "media_url": "",
                        "recomendation_media_url": "",
                        "related_recipe": null
                    },
                    {
                        "description": "1 sdm saos tiram",
                        "recommendation": "",
                        "brand": "",
                        "buy_url": "",
                        "media_url": "",
                        "recomendation_media_url": "",
                        "related_recipe": null
                    },
                    {
                        "description": "1\/4 sdt garam",
                        "recommendation": "",
                        "brand": "",
                        "buy_url": "",
                        "media_url": "",
                        "recomendation_media_url": "",
                        "related_recipe": null
                    },
                    {
                        "description": "1\/4 sdt kaldu bubuk",
                        "recommendation": "",
                        "brand": "",
                        "buy_url": "",
                        "media_url": "",
                        "recomendation_media_url": "",
                        "related_recipe": null
                    },
                    {
                        "description": "1\/4 sdt lada bubuk",
                        "recommendation": "",
                        "brand": "",
                        "buy_url": "",
                        "media_url": "",
                        "recomendation_media_url": "",
                        "related_recipe": null
                    },
                    {
                        "description": "1 sdm gula pasir",
                        "recommendation": "",
                        "brand": "",
                        "buy_url": "",
                        "media_url": "",
                        "recomendation_media_url": "",
                        "related_recipe": null
                    },
                    {
                        "description": "150 ml air",
                        "recommendation": "",
                        "brand": "",
                        "buy_url": "",
                        "media_url": "",
                        "recomendation_media_url": "",
                        "related_recipe": null
                    },
                    {
                        "description": "1 sdm larutan maizena",
                        "recommendation": "",
                        "brand": "",
                        "buy_url": "",
                        "media_url": "",
                        "recomendation_media_url": "",
                        "related_recipe": null
                    }
                ]
            }
        ],
        "nutrition": [],
        "recook": [],
        "cooking_tool": [],
        "tips_and_trick": [],
        "purchase_detail": []
    }
}