{
    "status": 200,
    "message": "success",
    "data": {
        "id": "zcB4aew7g--v6U_8BsEE6Q==",
        "title": "Tahu Telur Tomat Kuah",
        "slug": "tahu-telur-tomat-kuah",
        "cover_url": "content-images\/images\/20250415\/2qtfMmvoGGG0y9W1lRL6TLgkmRtOs9Q2-31373434363936393732d41d8cd98f00b204e9800998ecf8427e.jpg?x-oss-process=image\/format,webp",
        "cover_url_watermark": "content-images\/images\/20250415\/2qtfMmvoGGG0y9W1lRL6TLgkmRtOs9Q2-31373434363936393732d41d8cd98f00b204e9800998ecf8427e.jpg?x-oss-process=image\/resize,w_600,h_315,m_fill,image\/watermark,image_Y29udGVudC1pbWFnZXMvaW1hZ2VzLzIwMjMwNzMxL3dhdGVybWFyay1hcnRpY2xlLnBuZz94LW9zcy1wcm9jZXNzPWltYWdlL3Jlc2l6ZSxQXzEwMA==,g_south,y_0",
        "description": "Resep mudah, murah, sehat.",
        "rating": 5,
        "video_url": "",
        "price": 15000,
        "price_premium": 0,
        "calories": "",
        "is_cvc": false,
        "cooking_time": 30,
        "serving_min": 2,
        "serving_max": 3,
        "release_date": 1746590820,
        "updated_date": 1746591683,
        "is_bookmark": false,
        "is_editorial": false,
        "rating_user": 0,
        "is_video": false,
        "premium_content": false,
        "brand_slug": "",
        "ingredient_count": 9,
        "meta_title": "",
        "meta_description": "",
        "og_caption": "",
        "og_title": "",
        "og_description": "",
        "og_media": "",
        "rater_count": 1,
        "recook_count": 0,
        "original_image": "content-images\/images\/20250415\/2qtfMmvoGGG0y9W1lRL6TLgkmRtOs9Q2-31373434363936393732d41d8cd98f00b204e9800998ecf8427e.jpg?x-oss-process=image\/resize,w_800,h_800,m_fixed",
        "share_link": "https:\/\/app.yummy.co.id\/hRp921wb4YwjXzu88",
        "category": {
            "name": "",
            "slug": ""
        },
        "cooking_step": [
            {
                "title": "Langkah 1",
                "text": "Panaskan wajan, buat telur orak arik.",
                "image_url": "content-images\/images\/20250415\/UZTbMaQ91Uu78MdIgb3M6Gd0gXcTpCJg-31373434363937313634d41d8cd98f00b204e9800998ecf8427e.jpg?x-oss-process=image\/resize,w_600,h_600,m_fixed,image\/format,webp",
                "order": 1,
                "start_at": 0,
                "original_image": "content-images\/images\/20250415\/UZTbMaQ91Uu78MdIgb3M6Gd0gXcTpCJg-31373434363937313634d41d8cd98f00b204e9800998ecf8427e.jpg?x-oss-process=image\/format,webp"
            },
            {
                "title": "Langkah 2",
                "text": "Angkat dan sisihkan.",
                "image_url": "content-images\/images\/20250415\/PnwmE8vbtzqbROFhHpjdruC5E59h5TKH-31373434363937323137d41d8cd98f00b204e9800998ecf8427e.jpg?x-oss-process=image\/resize,w_600,h_600,m_fixed,image\/format,webp",
                "order": 2,
                "start_at": 0,
                "original_image": "content-images\/images\/20250415\/PnwmE8vbtzqbROFhHpjdruC5E59h5TKH-31373434363937323137d41d8cd98f00b204e9800998ecf8427e.jpg?x-oss-process=image\/format,webp"
            },
            {
                "title": "Langkah 3",
                "text": "Tumis bawang putih, daun bawang dan tomat hingga harum.",
                "image_url": "content-images\/images\/20250415\/vLQcGClpzOzgXRJKCkxobvUGEuv4LNMl-31373434363937323239d41d8cd98f00b204e9800998ecf8427e.jpg?x-oss-process=image\/resize,w_600,h_600,m_fixed,image\/format,webp",
                "order": 3,
                "start_at": 0,
                "original_image": "content-images\/images\/20250415\/vLQcGClpzOzgXRJKCkxobvUGEuv4LNMl-31373434363937323239d41d8cd98f00b204e9800998ecf8427e.jpg?x-oss-process=image\/format,webp"
            },
            {
                "title": "Langkah 4",
                "text": "Tambahkan air. Biarkan hingga mendidih.",
                "image_url": "content-images\/images\/20250415\/2bqMksjSLGhKW2nUZkRuM1Dhxpix05F3-31373434363937323536d41d8cd98f00b204e9800998ecf8427e.jpg?x-oss-process=image\/resize,w_600,h_600,m_fixed,image\/format,webp",
                "order": 4,
                "start_at": 0,
                "original_image": "content-images\/images\/20250415\/2bqMksjSLGhKW2nUZkRuM1Dhxpix05F3-31373434363937323536d41d8cd98f00b204e9800998ecf8427e.jpg?x-oss-process=image\/format,webp"
            },
            {
                "title": "Langkah 5",
                "text": "Tambahkan tahu dan telur orak arik. Masak sekitar 3 menit dengan api kecil.",
                "image_url": "content-images\/images\/20250415\/ZBaqkWCtLIT7G5GoPBiRGMf7ikx9kb5t-31373434363937323734d41d8cd98f00b204e9800998ecf8427e.jpg?x-oss-process=image\/resize,w_600,h_600,m_fixed,image\/format,webp",
                "order": 5,
                "start_at": 0,
                "original_image": "content-images\/images\/20250415\/ZBaqkWCtLIT7G5GoPBiRGMf7ikx9kb5t-31373434363937323734d41d8cd98f00b204e9800998ecf8427e.jpg?x-oss-process=image\/format,webp"
            },
            {
                "title": "Langkah 6",
                "text": "Koreksi rasa dan sajikn hangat. Jika ingin pedas bisa tambah potongan canai rawit.",
                "image_url": "content-images\/images\/20250415\/EJGrpoGEVwvS19WLDJ9c0AUvDXOtExCt-31373434363937323937d41d8cd98f00b204e9800998ecf8427e.jpg?x-oss-process=image\/resize,w_600,h_600,m_fixed,image\/format,webp",
                "order": 6,
                "start_at": 0,
                "original_image": "content-images\/images\/20250415\/EJGrpoGEVwvS19WLDJ9c0AUvDXOtExCt-31373434363937323937d41d8cd98f00b204e9800998ecf8427e.jpg?x-oss-process=image\/format,webp"
            }
        ],
        "tags": [
            {
                "id": "6aBOthKNa-VwyAhY6H31dA==",
                "name": "Makanan Utama",
                "slug": "makanan-utama"
            },
            {
                "id": "Jc3z7OQqbXF-iBXoiQkBZQ==",
                "name": "yummy tips",
                "slug": "yummy-tips"
            },
            {
                "id": "PnKlJFJzpnyBiz5TatWYnw==",
                "name": "Makanan Diet",
                "slug": "makanan-diet"
            },
            {
                "id": "eSjxzes6JPu0bFRNSnMkqg==",
                "name": "Makanan Anak Kost",
                "slug": "makanan-anak-kost"
            }
        ],
        "tag_ingredients": [
            {
                "id": "Nrc3f1w5lg_NgrGxtxmMhw==",
                "name": "Bawang Putih",
                "slug": "bawang-putih"
            },
            {
                "id": "eUDumVCs5n3IHcFz7LWG0A==",
                "name": "Tahu",
                "slug": "tahu"
            },
            {
                "id": "Bw86Nu0nb-A2uEVmsqabLQ==",
                "name": "Telur",
                "slug": "telur"
            },
            {
                "id": "0mFpKKHkQARg6xI2agSxcQ==",
                "name": "Tomat",
                "slug": "tomat"
            }
        ],
        "recipe_info": [],
        "author": {
            "id": "jif_DYfWXzuA4NgeM7kYLg==",
            "uuid": "91375c85-0409-4485-a153-7d0e57f531d3",
            "username": "lindaily",
            "name": "Lindaily",
            "avatar": "content-images\/avatar\/default.png?x-oss-process=image\/resize,w_200,h_200,m_fixed,image\/format,webp",
            "is_following": false,
            "is_official": false
        },
        "ingredient_type": [
            {
                "name": "Bahan Utama",
                "ingredients": [
                    {
                        "description": "2 butir telur",
                        "recommendation": "",
                        "brand": "",
                        "buy_url": "",
                        "media_url": "",
                        "recomendation_media_url": "",
                        "related_recipe": null
                    },
                    {
                        "description": "2 papan tahu (200gr) potong sesuai selera",
                        "recommendation": "",
                        "brand": "",
                        "buy_url": "",
                        "media_url": "",
                        "recomendation_media_url": "",
                        "related_recipe": null
                    },
                    {
                        "description": "2 buah tomat ukuran sedang, cincang kasar",
                        "recommendation": "",
                        "brand": "",
                        "buy_url": "",
                        "media_url": "",
                        "recomendation_media_url": "",
                        "related_recipe": null
                    },
                    {
                        "description": "1 siung bawang putih, cincang kasar",
                        "recommendation": "",
                        "brand": "",
                        "buy_url": "",
                        "media_url": "",
                        "recomendation_media_url": "",
                        "related_recipe": null
                    },
                    {
                        "description": "1 batang daun bawang, iris halus",
                        "recommendation": "",
                        "brand": "",
                        "buy_url": "",
                        "media_url": "",
                        "recomendation_media_url": "",
                        "related_recipe": null
                    },
                    {
                        "description": "250ml air",
                        "recommendation": "",
                        "brand": "",
                        "buy_url": "",
                        "media_url": "",
                        "recomendation_media_url": "",
                        "related_recipe": null
                    }
                ]
            },
            {
                "name": "Bumbu-Bumbu",
                "ingredients": [
                    {
                        "description": "1\/2 sdt garam",
                        "recommendation": "",
                        "brand": "",
                        "buy_url": "",
                        "media_url": "",
                        "recomendation_media_url": "",
                        "related_recipe": null
                    },
                    {
                        "description": "1 sdt saos tiram",
                        "recommendation": "",
                        "brand": "",
                        "buy_url": "",
                        "media_url": "",
                        "recomendation_media_url": "",
                        "related_recipe": null
                    },
                    {
                        "description": "1 sdt kecap asin",
                        "recommendation": "",
                        "brand": "",
                        "buy_url": "",
                        "media_url": "",
                        "recomendation_media_url": "",
                        "related_recipe": null
                    }
                ]
            }
        ],
        "nutrition": [],
        "recook": [],
        "cooking_tool": [],
        "tips_and_trick": [],
        "purchase_detail": []
    }
}